<?xml version="1.0" encoding="utf-8"?>
<search>
  
  
  
  <entry>
    <title>Diary</title>
    <link href="/2024/11/15/Diary/"/>
    <url>/2024/11/15/Diary/</url>
    
    <content type="html"><![CDATA[<p>“不愿放手 让命运去蹉跎</p><p>宁愿接受 有些人会爱错</p><p>至少我拥有一刻</p><p>拥抱着你的是我</p><p>不愿承认 其实我很脆弱</p><p>只顾追求 承诺的漩涡</p><p>直到爱悬在半空</p><p>任寂寞追逐的梦”</p><img src="/2024/11/15/Diary/4.png" class="">]]></content>
    
    
    <categories>
      
      <category>Life</category>
      
    </categories>
    
    
    <tags>
      
      <tag>InMyFeeling</tag>
      
    </tags>
    
  </entry>
  
  
  
  <entry>
    <title>Resonance</title>
    <link href="/2024/09/25/Resonance/"/>
    <url>/2024/09/25/Resonance/</url>
    
    <content type="html"><![CDATA[<p>“我不再将这个世界与我所期待的，塑造的圆满世界比照，而是接受这个世界，爱它，属于它。”</p><p>​——《悉达多》</p>]]></content>
    
    
    <categories>
      
      <category>Life</category>
      
    </categories>
    
    
    <tags>
      
      <tag>黑塞</tag>
      
    </tags>
    
  </entry>
  
  
  
  <entry>
    <title>Zayne</title>
    <link href="/2024/09/25/List/"/>
    <url>/2024/09/25/List/</url>
    
    <content type="html"><![CDATA[<p>黎医生好图分享~</p><img src="/2024/09/25/List/1.png" class=""><img src="/2024/09/25/List/2.png" class=""><img src="/2024/09/25/List/3.png" class="">]]></content>
    
    
    <categories>
      
      <category>Love&amp;Peace</category>
      
    </categories>
    
    
    <tags>
      
      <tag>黎深</tag>
      
    </tags>
    
  </entry>
  
  
  
  
</search>
